README.md
setup.cfg
setup.py
openapi_client/__init__.py
openapi_client/api_client.py
openapi_client/configuration.py
openapi_client/exceptions.py
openapi_client/rest.py
openapi_client/schemas.py
openapi_client/apis/__init__.py
openapi_client/apis/path_to_api.py
openapi_client/apis/tag_to_api.py
openapi_client/apis/paths/__init__.py
openapi_client/apis/paths/service_tunnel_id_security_policy.py
openapi_client/apis/paths/service_tunnel_id_security_policy_policy_id.py
openapi_client/apis/paths/v1_access_tiers_stats.py
openapi_client/apis/paths/v1_audit_logs.py
openapi_client/apis/paths/v1_delete_device.py
openapi_client/apis/paths/v1_delete_registered_service.py
openapi_client/apis/paths/v1_delete_security_attach_policy.py
openapi_client/apis/paths/v1_delete_security_policy.py
openapi_client/apis/paths/v1_delete_security_role.py
openapi_client/apis/paths/v1_device_id_token.py
openapi_client/apis/paths/v1_devices.py
openapi_client/apis/paths/v1_devices_stats.py
openapi_client/apis/paths/v1_disable_registered_service.py
openapi_client/apis/paths/v1_disable_security_role.py
openapi_client/apis/paths/v1_enable_registered_service.py
openapi_client/apis/paths/v1_enable_security_role.py
openapi_client/apis/paths/v1_enduser_devices.py
openapi_client/apis/paths/v1_enduser_devices_data.py
openapi_client/apis/paths/v1_endusers.py
openapi_client/apis/paths/v1_endusers_csv.py
openapi_client/apis/paths/v1_endusers_stats.py
openapi_client/apis/paths/v1_event_types.py
openapi_client/apis/paths/v1_events.py
openapi_client/apis/paths/v1_events_count.py
openapi_client/apis/paths/v1_events_feed.py
openapi_client/apis/paths/v1_insert_registered_service.py
openapi_client/apis/paths/v1_insert_saasapp.py
openapi_client/apis/paths/v1_insert_security_attach_policy.py
openapi_client/apis/paths/v1_insert_security_policy.py
openapi_client/apis/paths/v1_insert_security_role.py
openapi_client/apis/paths/v1_mdm_device_info.py
openapi_client/apis/paths/v1_mdm_insert_devices.py
pybanyan_client.egg-info/PKG-INFO
pybanyan_client.egg-info/SOURCES.txt
pybanyan_client.egg-info/dependency_links.txt
pybanyan_client.egg-info/requires.txt
pybanyan_client.egg-info/top_level.txt
