Metadata-Version: 2.1
Name: pybanyan-client
Version: 1.0.5
Summary: Banyan Rest APIs
Home-page: 
Author: OpenAPI Generator community
Author-email: team@openapitools.org
Keywords: OpenAPI,OpenAPI-Generator,Banyan Rest APIs
Requires-Python: >=3.7
